matrix_webhook_bot/__init__.py
matrix_webhook_bot/api.py
matrix_webhook_bot/logger.py
matrix_webhook_bot/main.py
matrix_webhook_bot/pickle_util.py
matrix_webhook_bot/webhook_bot.py
matrix_webhook_bot/config/sample_config.ini
matrix_webhook_bot/config/templates/emby.jinja
matrix_webhook_bot/config/templates/webhooks_message.jinja
matrix_webhook_bot-0.1.7.dist-info/METADATA
matrix_webhook_bot-0.1.7.dist-info/WHEEL
matrix_webhook_bot-0.1.7.dist-info/entry_points.txt
matrix_webhook_bot-0.1.7.dist-info/licenses/LICENSE
matrix_webhook_bot-0.1.7.dist-info/RECORD
