Metadata-Version: 2.4
Name: matrix-webhook-bot
Version: 0.1.7
Author: hidraulicChicken
License-File: LICENSE
Requires-Python: >=3.13
Requires-Dist: asyncpg<0.31,>=0.30.0
Requires-Dist: emoji<3,>=2.14.1
Requires-Dist: fastapi<0.116,>=0.115.6
Requires-Dist: httpx<0.29,>=0.28.1
Requires-Dist: jinja2<4,>=3.1.5
Requires-Dist: mautrix<0.21,>=0.20.7
Requires-Dist: python-olm<4,>=3.2.16
Requires-Dist: uvicorn<0.35,>=0.34.0
Provides-Extra: dev
Requires-Dist: black; extra == 'dev'
Requires-Dist: hatch; extra == 'dev'
Requires-Dist: pytest; extra == 'dev'
Requires-Dist: ruff; extra == 'dev'
